examples/byte_list.py
examples/from_file.py
tests/__init__.py
tests/test_connection.py
tests/test_options.py
tests/test_processed_data.py
tests/test_source_handler.py
tests/test_task_status_polling.py
tilt/__init__.py
tilt/async_executor.py
tilt/connection.py
tilt/console.py
tilt/endpoints.py
tilt/log.py
tilt/main.py
tilt/options.py
tilt/processed_data.py
tilt/sectioner.py
tilt/source_handler.py
tilt/tilt.py
tilt/types.py
tilt/utils.py
tilt/validator.py
tilt/entities/__init__.py
tilt/entities/auth.py
tilt/entities/job.py
tilt/entities/organization.py
tilt/entities/task.py
tilt/entities/user.py
tilt_py-0.1.2.dist-info/METADATA
tilt_py-0.1.2.dist-info/WHEEL
tilt_py-0.1.2.dist-info/top_level.txt
tilt_py-0.1.2.dist-info/RECORD
