Metadata-Version: 2.4
Name: tilt_py
Version: 0.1.2
Summary: Python client for processing and sending data to Tilt's distributed computing platform
Requires-Python: >=3.10
Requires-Dist: aiohttp>=3.8
Requires-Dist: aiofiles>=23.0
